{
  "src/devpanel.ts": {
    "max-lines-per-function": {
      "count": 1
    }
  },
  "src/ui/overlay.ts": {
    "complexity": {
      "count": 1
    }
  },
  "src/ui/questlog.ts": {
    "complexity": {
      "count": 1
    }
  },
  "src/ui/quiz.ts": {
    "complexity": {
      "count": 1
    }
  },
  "src/ui/radio.ts": {
    "complexity": {
      "count": 2
    }
  },
  "src/world/regions/archipel.ts": {
    "complexity": {
      "count": 1
    }
  },
  "src/world/regions/lighthouse.ts": {
    "complexity": {
      "count": 1
    }
  },
  "src/world/regions/warehouse.ts": {
    "complexity": {
      "count": 1
    }
  }
}